[
  {
    "Type": "DataTable",
    "Name": "1020AwakenEffect",
    "Flags": "RF_Public | RF_Standalone | RF_Transactional | RF_WasLoaded | RF_LoadCompleted",
    "Class": "UScriptClass'DataTable'",
    "Package": "/Game/DataTable/Character/Awaken/1020AwakenEffect",
    "Properties": {
      "RowStruct": {
        "ObjectName": "Class'CharacterAwakenEffectData'",
        "ObjectPath": "/Script/HTGame"
}
    },
    "Rows": {
      "1020": {
        "AwakenEffectStructList": [
          {
            "EffectID": "Effect1",
            "AwakenUnlockQuest": "None",
            "Title": {
              "TableId": "/Game/Text/PlayerSkillDes/Haniel_SkillDes.Haniel_SkillDes",
              "Key": "GA_Haniel_star1_name"
},
            "AwakenIcon": {
              "AssetPathName": "/Game/UI/UI/player/YH_UI_juexingICON/1020_1.1020_1",
              "SubPathString": ""
},
            "ModifyDataList": [
              {
                "Buff": {
                  "AssetPathName": "/Game/Blueprints/Abilities/Player/Ability_020_haniel/Upgrade/level1/Buff_Haniel020_Level1.Buff_Haniel020_Level1_C",
                  "SubPathString": ""
},
                "bReliveNeedAddAgain": false
}
            ],
            "AwakenType": "EAwakenEffect::Awaken_Effect",
            "Desc": {
              "TableId": "/Game/Text/PlayerSkillDes/Haniel_SkillDes.Haniel_SkillDes",
              "Key": "GA_Haniel_star1_des"
}
          },
          {
            "EffectID": "Effect2",
            "AwakenUnlockQuest": "None",
            "Title": {
              "TableId": "/Game/Text/PlayerSkillDes/Haniel_SkillDes.Haniel_SkillDes",
              "Key": "GA_Haniel_star2_name"
},
            "AwakenIcon": {
              "AssetPathName": "/Game/UI/UI/player/YH_UI_juexingICON/1020_2.1020_2",
              "SubPathString": ""
},
            "ModifyDataList": [
              {
                "Buff": {
                  "AssetPathName": "/Game/Blueprints/Abilities/Player/Ability_020_haniel/Upgrade/level2/Buff_Haniel020_Level2.Buff_Haniel020_Level2_C",
                  "SubPathString": ""
},
                "bReliveNeedAddAgain": false
}
            ],
            "AwakenType": "EAwakenEffect::Awaken_Effect",
            "Desc": {
              "TableId": "/Game/Text/PlayerSkillDes/Haniel_SkillDes.Haniel_SkillDes",
              "Key": "GA_Haniel_star2_des"
}
          },
          {
            "EffectID": "Effect3",
            "AwakenUnlockQuest": "None",
            "Title": {
              "TableId": "/Game/Text/PlayerSkillDes/Haniel_SkillDes.Haniel_SkillDes",
              "Key": "GA_Haniel_star3_name"
},
            "AwakenIcon": {
              "AssetPathName": "/Game/UI/UI/player/YH_UI_juexingICON/1020_3.1020_3",
              "SubPathString": ""
},
            "ModifyDataList": [
              {
                "Buff": {
                  "AssetPathName": "/Game/Blueprints/Abilities/Player/Ability_020_haniel/Upgrade/level3/Buff_Haniel020_Level3.Buff_Haniel020_Level3_C",
                  "SubPathString": ""
},
                "bReliveNeedAddAgain": false
}
            ],
            "AwakenType": "EAwakenEffect::Awaken_Effect",
            "Desc": {
              "TableId": "/Game/Text/PlayerSkillDes/Haniel_SkillDes.Haniel_SkillDes",
              "Key": "GA_Haniel_star3_des"
}
          },
          {
            "EffectID": "Effect4",
            "AwakenUnlockQuest": "None",
            "Title": {
              "TableId": "/Game/Text/PlayerSkillDes/Haniel_SkillDes.Haniel_SkillDes",
              "Key": "GA_Haniel_star4_name"
},
            "AwakenIcon": {
              "AssetPathName": "/Game/UI/UI/player/YH_UI_juexingICON/1020_4.1020_4",
              "SubPathString": ""
},
            "ModifyDataList": [
              {
                "Buff": {
                  "AssetPathName": "/Game/Blueprints/Abilities/Player/Ability_020_haniel/Upgrade/level4/Buff_Haniel020_Level4.Buff_Haniel020_Level4_C",
                  "SubPathString": ""
},
                "bReliveNeedAddAgain": false
}
            ],
            "AwakenType": "EAwakenEffect::Awaken_Effect",
            "Desc": {
              "TableId": "/Game/Text/PlayerSkillDes/Haniel_SkillDes.Haniel_SkillDes",
              "Key": "GA_Haniel_star4_des"
}
          },
          {
            "EffectID": "Effect5",
            "AwakenUnlockQuest": "None",
            "Title": {
              "TableId": "/Game/Text/PlayerSkillDes/Haniel_SkillDes.Haniel_SkillDes",
              "Key": "GA_Haniel_star5_name"
},
            "AwakenIcon": {
              "AssetPathName": "/Game/UI/UI/player/YH_UI_juexingICON/1020_5.1020_5",
              "SubPathString": ""
},
            "ModifyDataList": [
              {
                "Buff": {
                  "AssetPathName": "/Game/Blueprints/Abilities/Player/Ability_020_haniel/Upgrade/level5/Buff_Haniel020_Level5.Buff_Haniel020_Level5_C",
                  "SubPathString": ""
},
                "bReliveNeedAddAgain": false
}
            ],
            "AwakenType": "EAwakenEffect::Awaken_Effect",
            "Desc": {
              "TableId": "/Game/Text/PlayerSkillDes/Haniel_SkillDes.Haniel_SkillDes",
              "Key": "GA_Haniel_star5_des"
}
          },
          {
            "EffectID": "Effect6",
            "AwakenUnlockQuest": "None",
            "Title": {
              "TableId": "/Game/Text/PlayerSkillDes/Haniel_SkillDes.Haniel_SkillDes",
              "Key": "GA_Haniel_star6_name"
},
            "AwakenIcon": {
              "AssetPathName": "/Game/UI/UI/player/YH_UI_juexingICON/1020_6.1020_6",
              "SubPathString": ""
},
            "ModifyDataList": [
              {
                "Buff": {
                  "AssetPathName": "/Game/Blueprints/Abilities/Player/Ability_020_haniel/Upgrade/level6/Buff_Haniel020_Level6.Buff_Haniel020_Level6_C",
                  "SubPathString": ""
},
                "bReliveNeedAddAgain": false
}
            ],
            "AwakenType": "EAwakenEffect::Awaken_Effect",
            "Desc": {
              "TableId": "/Game/Text/PlayerSkillDes/Haniel_SkillDes.Haniel_SkillDes",
              "Key": "GA_Haniel_star6_des"
}
          },
          {
            "EffectID": "resonance_3",
            "AwakenUnlockQuest": "None",
            "Title": {
              "TableId": "/Game/Text/PlayerSkillDes/Haniel_SkillDes.Haniel_SkillDes",
              "Key": "GA_Haniel_starExtra1_name"
},
            "AwakenIcon": {
              "AssetPathName": "/Game/UI/UI/player/YH_UI_juexingICON/1009_2.1009_2",
              "SubPathString": ""
},
            "ModifyDataList": [
              {
                "SkillName": "GA_Haniel_Melee",
                "SkillLevel": 1
},
              {
                "SkillName": "GA_Haniel_Skill",
                "SkillLevel": 1
},
              {
                "SkillName": "GA_Haniel_UltraSkill",
                "SkillLevel": 1
}
            ],
            "AwakenType": "EAwakenEffect::Awaken_Resonance",
            "Desc": {
              "TableId": "/Game/Text/PlayerSkillDes/Haniel_SkillDes.Haniel_SkillDes",
              "Key": "GA_Haniel_starExtra1_des"
}
          },
          {
            "EffectID": "resonance_6",
            "AwakenUnlockQuest": "None",
            "Title": {
              "TableId": "/Game/Text/PlayerSkillDes/Haniel_SkillDes.Haniel_SkillDes",
              "Key": "GA_Haniel_starExtra2_name"
},
            "AwakenIcon": {
              "AssetPathName": "/Game/UI/UI/player/YH_UI_juexingICON/1009_2.1009_2",
              "SubPathString": ""
},
            "ModifyDataList": [
              {
                "Buff": {
                  "AssetPathName": "/Game/Blueprints/Abilities/Player/Ability_020_haniel/Upgrade/Levelex/Buff_haniel_LevelExtra.Buff_haniel_LevelExtra_C",
                  "SubPathString": ""
},
                "bReliveNeedAddAgain": false
}
            ],
            "AwakenType": "EAwakenEffect::Awaken_Resonance",
            "Desc": {
              "TableId": "/Game/Text/PlayerSkillDes/Haniel_SkillDes.Haniel_SkillDes",
              "Key": "GA_Haniel_starExtra2_des"
}
          }
        ]
      }
    }
  }
]