[
  {
    "Type": "DataTable",
    "Name": "DT_TrialCloneDataTable",
    "Flags": "RF_Public | RF_Standalone | RF_Transactional | RF_WasLoaded | RF_LoadCompleted",
    "Class": "UScriptClass'DataTable'",
    "Package": "/Game/DataTable/Character/Trial/DT_TrialCloneDataTable",
    "Properties": {
      "RowStruct": {
        "ObjectName": "Class'TrialCharacterCloneDataTable'",
        "ObjectPath": "/Script/HTGame"
      }
    },
    "Rows": {
      "TrialClone01": {
        "TrialID": "Trial01",
        "MonsterID": "BeParryAttackMonster",
        "CloneSystemID": "TeachClone"
      },
      "TrialTeach01": {
        "TrialID": "Trial01_Boss06",
        "MonsterID": "TrailTeach01_MonsterWood_01",
        "CloneSystemID": "TeachClone"
      },
      "AdlerClone": {
        "TrialID": "TeachChar_Adler",
        "MonsterID": "TrailTeach01_MonsterWood_01",
        "CloneSystemID": "TeachClone"
      },
      "CangClone": {
        "TrialID": "TeachChar_Cang",
        "MonsterID": "TrailTeach01_MonsterWood_01",
        "CloneSystemID": "TeachClone"
      },
      "SkiaClone": {
        "TrialID": "TeachChar_Skia",
        "MonsterID": "TrailTeach01_MonsterWood_01",
        "CloneSystemID": "TeachClone"
      },
      "FadiaClone": {
        "TrialID": "TeachChar_Fadia_single",
        "MonsterID": "TrailTeach01_MonsterWood_01",
        "CloneSystemID": "TeachClone"
      },
      "GeneralClone": {
        "TrialID": "TeachChar_ring_single",
        "MonsterID": "TrailTeach01_MonsterWood_01",
        "CloneSystemID": "TeachClone"
      },
      "XunClone": {
        "TrialID": "TeachChar_Jin_single",
        "MonsterID": "TrailTeach01_MonsterWood_01",
        "CloneSystemID": "TeachClone"
      },
      "NanaliClone": {
        "TrialID": "TeachChar_Nanali",
        "MonsterID": "TrailTeach01_MonsterWood_01",
        "CloneSystemID": "TeachClone"
      },
      "SagiriClone": {
        "TrialID": "TeachChar_Sagiri",
        "MonsterID": "TrailTeach01_MonsterWood_01",
        "CloneSystemID": "TeachClone"
      },
      "MintClone": {
        "TrialID": "TeachChar_Mint",
        "MonsterID": "TrailTeach01_MonsterWood_01",
        "CloneSystemID": "TeachClone"
      },
      "EdgarClone": {
        "TrialID": "TeachChar_edgar",
        "MonsterID": "TrailTeach01_MonsterWood_01",
        "CloneSystemID": "TeachClone"
      },
      "KuharaClone": {
        "TrialID": "TeachChar_Kuhara_single",
        "MonsterID": "TrailTeach01_MonsterWood_01",
        "CloneSystemID": "TeachClone"
      },
      "Chiichan073Clone": {
        "TrialID": "TeachChar_Chiichan073",
        "MonsterID": "TrailTeach01_MonsterWood_01",
        "CloneSystemID": "TeachClone"
      },
      "ReactionguanglingClone": {
        "TrialID": "Teach_ring_main",
        "MonsterID": "TrailTeach01_MonsterWood_01",
        "CloneSystemID": "TeachClone"
      },
      "ReactionguangxiangClone": {
        "TrialID": "Teach_ring_main",
        "MonsterID": "TrailTeach01_MonsterWood_01",
        "CloneSystemID": "TeachClone"
      },
      "ReactionlingzhouClone": {
        "TrialID": "Teach_ring_main",
        "MonsterID": "TrailTeach01_MonsterWood_01",
        "CloneSystemID": "TeachClone"
      },
      "ReactionanhunClone": {
        "TrialID": "Teach_ring_main",
        "MonsterID": "TrailTeach01_MonsterWood_01",
        "CloneSystemID": "TeachClone"
      },
      "ReactionanzhouClone": {
        "TrialID": "Teach_ring_main",
        "MonsterID": "TrailTeach01_MonsterWood_01",
        "CloneSystemID": "TeachClone"
      },
      "ReactionhunxiangClone": {
        "TrialID": "Teach_ring_main",
        "MonsterID": "TrailTeach01_MonsterWood_01",
        "CloneSystemID": "TeachClone"
      },
      "ReactionguanglingxiangClone": {
        "TrialID": "Teach_ring_main",
        "MonsterID": "TrailTeach01_MonsterWood_01",
        "CloneSystemID": "TeachClone"
      },
      "ReactionanhunzhouClone": {
        "TrialID": "Teach_ring_main",
        "MonsterID": "TrailTeach01_MonsterWood_01",
        "CloneSystemID": "TeachClone"
      },
      "HathorClone": {
        "TrialID": "TeachChar_hathor",
        "MonsterID": "TrailTeach01_MonsterWood_01",
        "CloneSystemID": "TeachClone"
      },
      "DaffodillClone": {
        "TrialID": "TeachChar_daffodill_single",
        "MonsterID": "TrailTeach01_MonsterWood_01",
        "CloneSystemID": "TeachClone"
      }
    }
  }
]