[
  {
    "Type": "CurveFloat",
    "Name": "FFE_Sagiri_A4",
    "Flags": "RF_Public | RF_Standalone | RF_Transactional | RF_WasLoaded | RF_LoadCompleted",
    "Class": "UScriptClass'CurveFloat'",
    "Package": "/Game/DataAssets/DataAssetSet/Gamepad/Feedback/FFE_Sagiri/FFE_Sagiri_A4",
    "Properties": {
      "FloatCurve": {
        "Keys": [
          {
            "InterpMode": "RCIM_Linear",
            "TangentMode": "RCTM_Auto",
            "TangentWeightMode": "RCTWM_WeightedNone",
            "Time": 0.0,
            "Value": 2.0,
            "ArriveTangent": -6.666666,
            "ArriveTangentWeight": 0.0,
            "LeaveTangent": 0.0,
            "LeaveTangentWeight": 0.0
          },
          {
            "InterpMode": "RCIM_Linear",
            "TangentMode": "RCTM_Auto",
            "TangentWeightMode": "RCTWM_WeightedNone",
            "Time": 0.1,
            "Value": 9.2546834E-08,
            "ArriveTangent": 0.0,
            "ArriveTangentWeight": 0.0,
            "LeaveTangent": 0.0,
            "LeaveTangentWeight": 0.0
          }
        ]
      }
    }
  }
]