[
  {
    "Type": "DataTable",
    "Name": "DT_RacingPVPStaminaAward",
    "Flags": "RF_Public | RF_Standalone | RF_Transactional | RF_WasLoaded | RF_LoadCompleted",
    "Class": "UScriptClass'DataTable'",
    "Package": "/Game/DataTable/Racing/DT_RacingPVPStaminaAward",
    "Properties": {
      "RowStruct": {
        "ObjectName": "Class'RacingPVPStaminaAwardData'",
        "ObjectPath": "/Script/HTGame"
      }
    },
    "Rows": {
      "R1_100": {
        "Rank": 1,
        "ProgressRange": {
          "LowerBound": {
            "Type": "ERangeBoundTypes::Exclusive",
            "Value": 0.5
          },
          "UpperBound": {
            "Type": "ERangeBoundTypes::Inclusive",
            "Value": 1.0
          }
        },
        "CostStaminaID": "CityStamina",
        "CostStaminaAmountBase": 20
      },
      "R1_50": {
        "Rank": 1,
        "ProgressRange": {
          "LowerBound": {
            "Type": "ERangeBoundTypes::Exclusive",
            "Value": 0.25
          },
          "UpperBound": {
            "Type": "ERangeBoundTypes::Inclusive",
            "Value": 0.5
          }
        },
        "CostStaminaID": "CityStamina",
        "CostStaminaAmountBase": 15
      },
      "R1_25": {
        "Rank": 1,
        "ProgressRange": {
          "LowerBound": {
            "Type": "ERangeBoundTypes::Exclusive",
            "Value": 0.05
          },
          "UpperBound": {
            "Type": "ERangeBoundTypes::Inclusive",
            "Value": 0.25
          }
        },
        "CostStaminaID": "CityStamina",
        "CostStaminaAmountBase": 10
      },
      "R1_5": {
        "Rank": 1,
        "ProgressRange": {
          "LowerBound": {
            "Type": "ERangeBoundTypes::Inclusive",
            "Value": 0.0
          },
          "UpperBound": {
            "Type": "ERangeBoundTypes::Inclusive",
            "Value": 0.05
          }
        },
        "CostStaminaID": "CityStamina",
        "CostStaminaAmountBase": 0
      },
      "R2_100": {
        "Rank": 2,
        "ProgressRange": {
          "LowerBound": {
            "Type": "ERangeBoundTypes::Exclusive",
            "Value": 0.8
          },
          "UpperBound": {
            "Type": "ERangeBoundTypes::Inclusive",
            "Value": 1.0
          }
        },
        "CostStaminaID": "CityStamina",
        "CostStaminaAmountBase": 18
      },
      "R2_80": {
        "Rank": 2,
        "ProgressRange": {
          "LowerBound": {
            "Type": "ERangeBoundTypes::Exclusive",
            "Value": 0.5
          },
          "UpperBound": {
            "Type": "ERangeBoundTypes::Inclusive",
            "Value": 0.8
          }
        },
        "CostStaminaID": "CityStamina",
        "CostStaminaAmountBase": 15
      },
      "R2_50": {
        "Rank": 2,
        "ProgressRange": {
          "LowerBound": {
            "Type": "ERangeBoundTypes::Exclusive",
            "Value": 0.2
          },
          "UpperBound": {
            "Type": "ERangeBoundTypes::Inclusive",
            "Value": 0.5
          }
        },
        "CostStaminaID": "CityStamina",
        "CostStaminaAmountBase": 12
      },
      "R2_20": {
        "Rank": 2,
        "ProgressRange": {
          "LowerBound": {
            "Type": "ERangeBoundTypes::Inclusive",
            "Value": 0.0
          },
          "UpperBound": {
            "Type": "ERangeBoundTypes::Inclusive",
            "Value": 0.2
          }
        },
        "CostStaminaID": "CityStamina",
        "CostStaminaAmountBase": 0
      },
      "R3_100": {
        "Rank": 3,
        "ProgressRange": {
          "LowerBound": {
            "Type": "ERangeBoundTypes::Inclusive",
            "Value": 0.8
          },
          "UpperBound": {
            "Type": "ERangeBoundTypes::Inclusive",
            "Value": 1.0
          }
        },
        "CostStaminaID": "CityStamina",
        "CostStaminaAmountBase": 16
      },
      "R3_80": {
        "Rank": 3,
        "ProgressRange": {
          "LowerBound": {
            "Type": "ERangeBoundTypes::Exclusive",
            "Value": 0.5
          },
          "UpperBound": {
            "Type": "ERangeBoundTypes::Inclusive",
            "Value": 0.8
          }
        },
        "CostStaminaID": "CityStamina",
        "CostStaminaAmountBase": 13
      },
      "R3_50": {
        "Rank": 3,
        "ProgressRange": {
          "LowerBound": {
            "Type": "ERangeBoundTypes::Inclusive",
            "Value": 0.2
          },
          "UpperBound": {
            "Type": "ERangeBoundTypes::Inclusive",
            "Value": 0.5
          }
        },
        "CostStaminaID": "CityStamina",
        "CostStaminaAmountBase": 10
      },
      "R3_20": {
        "Rank": 3,
        "ProgressRange": {
          "LowerBound": {
            "Type": "ERangeBoundTypes::Inclusive",
            "Value": 0.0
          },
          "UpperBound": {
            "Type": "ERangeBoundTypes::Inclusive",
            "Value": 0.2
          }
        },
        "CostStaminaID": "CityStamina",
        "CostStaminaAmountBase": 0
      },
      "R4_100": {
        "Rank": 4,
        "ProgressRange": {
          "LowerBound": {
            "Type": "ERangeBoundTypes::Inclusive",
            "Value": 0.8
          },
          "UpperBound": {
            "Type": "ERangeBoundTypes::Inclusive",
            "Value": 1.0
          }
        },
        "CostStaminaID": "CityStamina",
        "CostStaminaAmountBase": 15
      },
      "R4_80": {
        "Rank": 4,
        "ProgressRange": {
          "LowerBound": {
            "Type": "ERangeBoundTypes::Inclusive",
            "Value": 0.5
          },
          "UpperBound": {
            "Type": "ERangeBoundTypes::Inclusive",
            "Value": 0.8
          }
        },
        "CostStaminaID": "CityStamina",
        "CostStaminaAmountBase": 12
      },
      "R4_50": {
        "Rank": 4,
        "ProgressRange": {
          "LowerBound": {
            "Type": "ERangeBoundTypes::Inclusive",
            "Value": 0.2
          },
          "UpperBound": {
            "Type": "ERangeBoundTypes::Inclusive",
            "Value": 0.5
          }
        },
        "CostStaminaID": "CityStamina",
        "CostStaminaAmountBase": 8
      },
      "R4_20": {
        "Rank": 4,
        "ProgressRange": {
          "LowerBound": {
            "Type": "ERangeBoundTypes::Inclusive",
            "Value": 0.0
          },
          "UpperBound": {
            "Type": "ERangeBoundTypes::Inclusive",
            "Value": 0.2
          }
        },
        "CostStaminaID": "CityStamina",
        "CostStaminaAmountBase": 0
      }
    }
  }
]