[
  {
    "Type": "DataTable",
    "Name": "DT_ItemFunctionInputAction",
    "Flags": "RF_Public | RF_Standalone | RF_Transactional | RF_WasLoaded | RF_LoadCompleted",
    "Class": "UScriptClass'DataTable'",
    "Package": "/Game/DataAssets/DataAssetSet/Gamepad/ItemFunctionInputAction/DT_ItemFunctionInputAction",
    "Properties": {
      "RowStruct": {
        "ObjectName": "Class'ItemFunctionInputAction'",
        "ObjectPath": "/Script/HTGame"
      }
    },
    "Rows": {
      "Use": {
        "Key": {
          "KeyName": "Gamepad_FaceButton_Left"
        }
      },
      "Develop": {
        "Key": {
          "KeyName": "Gamepad_FaceButton_Top"
        }
      },
      "Details": {
        "Key": {
          "KeyName": "Gamepad_FaceButton_Top"
        }
      },
      "CookBook": {
        "Key": {
          "KeyName": "Gamepad_FaceButton_Top"
        }
      },
      "Return": {
        "Key": {
          "KeyName": "Gamepad_FaceButton_Top"
        }
      }
    }
  }
]