[
  {
    "Type": "HTSceneSolelyDataAsset",
    "Name": "SceneSolelyDataAsset_Clone",
    "Flags": "RF_Public | RF_Standalone | RF_Transactional | RF_WasLoaded | RF_LoadCompleted",
    "Class": "UScriptClass'HTSceneSolelyDataAsset'",
    "Package": "/Game/DataAssets/SceneSolelyDataAsset_Clone",
    "Properties": {
      "MonsterArrayDataTable": [
        {
          "ObjectName": "DataTable'DT_MonsterStaticData_Clone'",
          "ObjectPath": "/Game/DataTable/Monster/DT_MonsterStaticData_Clone.0"
        }
      ],
      "MonsterDropBoxDataTable": {
        "ObjectName": "DataTable'DT_MonsterDropBox'",
        "ObjectPath": "/Game/DataTable/Monster/DT_MonsterDropBox.0"
      },
      "DT_GuideDataTable": {
        "ObjectName": "DataTable'DT_GuideDataTable'",
        "ObjectPath": "/Game/DataTable/Guide/DT_GuideDataTable.0"
      }
    }
  }
]