[
  {
    "Type": "RandomItemDataAsset",
    "Name": "DA_RandomItem",
    "Flags": "RF_Public | RF_Standalone | RF_Transactional | RF_WasLoaded | RF_LoadCompleted",
    "Class": "UScriptClass'RandomItemDataAsset'",
    "Package": "/Game/DataAssets/DataAssetSet/RandomItem/DA_RandomItem",
    "Properties": {
      "DynamicCheckDist": 5000.0,
      "RandomItemDataTable": {
        "ObjectName": "DataTable'DT_RandomItem'",
        "ObjectPath": "/Game/DataAssets/DataAssetSet/RandomItem/DT_RandomItem.0"
      },
      "RandomItemTypeDataTable": {
        "ObjectName": "DataTable'DT_RandomItemType'",
        "ObjectPath": "/Game/DataAssets/DataAssetSet/RandomItem/DT_RandomItemType.0"
      },
      "RandomItemDropDataTable": {
        "ObjectName": "DataTable'DT_RandomItemDrop'",
        "ObjectPath": "/Game/DataAssets/DataAssetSet/RandomItem/DT_RandomItemDrop.0"
      },
      "PointTreasureBoxDataTable": {
        "ObjectName": "DataTable'DT_PointTreasureBox'",
        "ObjectPath": "/Game/DataAssets/DataAssetSet/RandomItem/DT_PointTreasureBox.0"
      }
    }
  }
]