[
  {
    "Type": "DataTable",
    "Name": "DT_ItemSortType",
    "Flags": "RF_Public | RF_Standalone | RF_Transactional | RF_WasLoaded | RF_LoadCompleted",
    "Class": "UScriptClass'DataTable'",
    "Package": "/Game/DataTable/Inventory/DT_ItemSortType",
    "Properties": {
      "RowStruct": {
        "ObjectName": "Class'ItemSortTypeData'",
        "ObjectPath": "/Script/HTGame"
}
    },
    "Rows": {
      "Quality": {
        "TypeName": {
          "TableId": "/Game/Text/ST_Ui.ST_Ui",
          "Key": "bag_07"
},
        "MapID": "None"
},
      "Level": {
        "TypeName": {
          "TableId": "/Game/Text/ST_Ui.ST_Ui",
          "Key": "bag_08"
},
        "MapID": "None"
},
      "Default": {
        "TypeName": {
          "TableId": "/Game/Text/ST_Ui.ST_Ui",
          "Key": "bag_17"
},
        "MapID": "None"
}
    }
  }
]